agstd/__init__.py
agstd/cli.py
agstd/config.py
agstd/decorators.py
agstd/events.py
agstd/log.py
agstd/main.py
agstd/persistance.py
agstd/refraction/__init__.py
agstd/refraction/refraction.py
agstd/refraction/txtbase2.py
agstd/sdb/#sqldbase.py#
agstd/sdb/__init__.py
agstd/sdb/dbase.py
agstd/sdb/sqldbase.py
agstd/text.py
agstd/vis/pipeline.py
agstd/vis/pipeline_examples/simple_surface.xml
agstd/xml.py
agstd-1.0.4.dist-info/WHEEL
agstd-1.0.4.dist-info/METADATA
agstd-1.0.4.dist-info/RECORD
