Metadata-Version: 2.1
Name: agstd
Version: 1.0.4
Summary: 
Author: Your Name
Author-email: you@example.com
Requires-Python: >=3.8,<3.11
Classifier: Programming Language :: Python :: 3
Classifier: Programming Language :: Python :: 3.10
Classifier: Programming Language :: Python :: 3.8
Classifier: Programming Language :: Python :: 3.9
Requires-Dist: numpy (>=1.22.2,<2.0.0)
Requires-Dist: pysqlite3 (>=0.4.6,<0.5.0)
Requires-Dist: tables (>=3.7.0,<4.0.0)
